[
   {
      "pkAssetHistoryDetailId":63,
      "fkAssetId":{
         "pkAssetId":1,
         "fkAssetType":{
            "pkAssetTypeId":1,
            "assetType":"Truck"
         },
         "assetName":"Truck1",
         "assetContactDetail":null
      },
      "timeOfTracking":"2021-03-06T17:05:06.000+00:00",
      "latitude": 19.153271108404777, 
      "longitude":72.9661974555075
   },
   {
      "pkAssetHistoryDetailId":67,
      "fkAssetId":{
         "pkAssetId":1,
         "fkAssetType":{
            "pkAssetTypeId":1,
            "assetType":"Truck"
         },
         "assetName":"Truck1",
         "assetContactDetail":null
      },
      "timeOfTracking":"2021-03-06T17:05:14.000+00:00",
      "latitude":19.1528371857218,
      "longitude":72.96913674487428
   },
   {
      "pkAssetHistoryDetailId":71,
      "fkAssetId":{
         "pkAssetId":1,
         "fkAssetType":{
            "pkAssetTypeId":1,
            "assetType":"Truck"
         },
         "assetName":"Truck1",
         "assetContactDetail":null
      },
      "timeOfTracking":"2021-03-06T17:05:17.000+00:00",
      "latitude":19.15226962697564,
      "longitude":72.97231248034791
   },
   {
      "pkAssetHistoryDetailId":75,
      "fkAssetId":{
         "pkAssetId":1,
         "fkAssetType":{
            "pkAssetTypeId":1,
            "assetType":"Truck"
         },
         "assetName":"Truck1",
         "assetContactDetail":null
      },
      "timeOfTracking":"2021-03-06T17:05:19.000+00:00",
      "latitude":19.15179278422838,
      "longitude":72.97359466552734

   },
   {
      "pkAssetHistoryDetailId":79,
      "fkAssetId":{
         "pkAssetId":1,
         "fkAssetType":{
            "pkAssetTypeId":1,
            "assetType":"Truck"
         },
         "assetName":"Truck1",
         "assetContactDetail":null
      },
      "timeOfTracking":"2021-03-06T17:05:22.000+00:00",
      "latitude":19.15159008361711,
      "longitude":72.97574050322163
   },
   {
      "pkAssetHistoryDetailId":83,
      "fkAssetId":{
         "pkAssetId":1,
         "fkAssetType":{
            "pkAssetTypeId":1,
            "assetType":"Truck"
         },
         "assetName":"Truck1",
         "assetContactDetail":null
      },
      "timeOfTracking":"2021-03-06T17:05:24.000+00:00",
      "latitude":19.177922657446853,
      "longitude":72.97359466552734
   }
]